Snoopy/__init__.py
Snoopy/version.py
Snoopy/DLLs/_Geometry.cp312-win_amd64.pyd
Snoopy/DLLs/_Geometry.cp313-win_amd64.pyd
Snoopy/DLLs/_Math.cp312-win_amd64.pyd
Snoopy/DLLs/_Math.cp313-win_amd64.pyd
Snoopy/DLLs/_Mechanics.cp312-win_amd64.pyd
Snoopy/DLLs/_Mechanics.cp313-win_amd64.pyd
Snoopy/DLLs/_Meshing.cp312-win_amd64.pyd
Snoopy/DLLs/_Meshing.cp313-win_amd64.pyd
Snoopy/DLLs/_Spectral.cp312-win_amd64.pyd
Snoopy/DLLs/_Spectral.cp313-win_amd64.pyd
Snoopy/DLLs/_Statistics.cp312-win_amd64.pyd
Snoopy/DLLs/_Statistics.cp313-win_amd64.pyd
Snoopy/DLLs/_TimeDomain.cp312-win_amd64.pyd
Snoopy/DLLs/_TimeDomain.cp313-win_amd64.pyd
Snoopy/DLLs/_WaveKinematic.cp312-win_amd64.pyd
Snoopy/DLLs/_WaveKinematic.cp313-win_amd64.pyd
Snoopy/Dataset/__init__.py
Snoopy/Dataset/rec34_rev2.csv
Snoopy/Dataset/rec34_rev2_hs05.csv
Snoopy/Fatigue/__init__.py
Snoopy/Fatigue/rainflow.py
Snoopy/Fatigue/sn_curve.py
Snoopy/Geometry/__init__.py
Snoopy/Geometry/sx3Manipulation.py
Snoopy/Math/Functions.py
Snoopy/Math/_HLCL.py
Snoopy/Math/_MHLGA.py
Snoopy/Math/__init__.py
Snoopy/Math/cmplxInterp.py
Snoopy/Math/interpolate.py
Snoopy/Math/iso_contour.py
Snoopy/Math/numerical_jacobian.py
Snoopy/Math/numpy_related.py
Snoopy/Math/spherical_coordinates.py
Snoopy/Mechanics/ReferenceFrameTools.py
Snoopy/Mechanics/__init__.py
Snoopy/Mechanics/hydro_coef.py
Snoopy/Mechanics/hydro_coef_io.py
Snoopy/Mechanics/hydro_data.csv
Snoopy/Mechanics/internal_load.py
Snoopy/Mechanics/mass_distribution.py
Snoopy/Mechanics/mass_section.py
Snoopy/Mechanics/matrans.py
Snoopy/Mechanics/mechanicalsolver.py
Snoopy/Meshing/__init__.py
Snoopy/Meshing/balance.py
Snoopy/Meshing/hsbln.py
Snoopy/Meshing/hydroStarMesh.py
Snoopy/Meshing/hydro_names.py
Snoopy/Meshing/mesh.py
Snoopy/Meshing/mesh_io.py
Snoopy/Meshing/reorder_nodes.py
Snoopy/Meshing/structuredGrid.py
Snoopy/Meshing/vtkTools.py
Snoopy/Meshing/vtkView.py
Snoopy/Meshing/vtk_fs_tools.py
Snoopy/Meshing/waterline.py
Snoopy/PyplotTools/__init__.py
Snoopy/PyplotTools/_scatterPlot.py
snoopy_bv-2.4.1.dist-info/LICENSE
snoopy_bv-2.4.1.dist-info/METADATA
snoopy_bv-2.4.1.dist-info/WHEEL
snoopy_bv-2.4.1.dist-info/top_level.txt
snoopy_bv-2.4.1.dist-info/RECORD
