Metadata-Version: 2.1
Name: snoopy-bv
Version: 2.4.1
Summary: DR C++/Python library
Home-page: https://gitlab.com/bv-dr/Snoopy
Author: Research Department BV M&O
Author-email: 
Classifier: Intended Audience :: Science/Research
Classifier: Topic :: Scientific/Engineering
Classifier: License :: OSI Approved :: GNU General Public License v3 or later (GPLv3+)
Classifier: Programming Language :: Python :: 3.11
Classifier: Operating System :: Microsoft :: Windows
License-File: LICENSE
Requires-Dist: xarray
Requires-Dist: numpy
Requires-Dist: scipy
Requires-Dist: pandas
Requires-Dist: matplotlib
Requires-Dist: h5py
Requires-Dist: tqdm
Requires-Dist: Deprecated
